AsyncDFD/__init__.py
AsyncDFD/abstract_node.py
AsyncDFD/analyser.py
AsyncDFD/decorator.py
AsyncDFD/exceptions.py
AsyncDFD/graph.py
AsyncDFD/label.py
AsyncDFD/node.py
AsyncDFD/node_group.py
AsyncDFD/node_transferable.py
AsyncDFD/pipeline.py
AsyncDFD-0.1.dist-info/LICENSE
AsyncDFD-0.1.dist-info/METADATA
AsyncDFD-0.1.dist-info/WHEEL
AsyncDFD-0.1.dist-info/top_level.txt
AsyncDFD-0.1.dist-info/RECORD
