Metadata-Version: 2.1
Name: AsyncDFD
Version: 0.1
Summary: A library for async accelerate based on gevent coroutine in python.
Home-page: https://github.com/R0k1e/AsyncDFD.git
Author: Haoyu Wang
Author-email: Haoyu_Wang_1103@outlook.com
Classifier: Programming Language :: Python :: 3
Classifier: License :: OSI Approved :: MIT License
Classifier: Operating System :: OS Independent
Requires-Python: >=3.11
License-File: LICENSE
Requires-Dist: gevent
Requires-Dist: tabulate
Requires-Dist: tenacity
